hell_hound/__init__.py
hell_hound/main.py
hell_hound/metadata.py
hell_hound-0.1.0.dist-info/LICENSE
hell_hound-0.1.0.dist-info/METADATA
hell_hound-0.1.0.dist-info/WHEEL
hell_hound-0.1.0.dist-info/entry_points.txt
hell_hound-0.1.0.dist-info/top_level.txt
hell_hound-0.1.0.dist-info/RECORD
